ladybug_vtk/__init__.py
ladybug_vtk/__main__.py
ladybug_vtk/_extend_hourly_plot.py
ladybug_vtk/_extend_ladybug_display.py
ladybug_vtk/_extend_ladybug_geometry.py
ladybug_vtk/_extend_sunpath.py
ladybug_vtk/_extend_visualization_set.py
ladybug_vtk/display_polydata.py
ladybug_vtk/from_display_geometry.py
ladybug_vtk/from_geometry.py
ladybug_vtk/fromgeometry.py
ladybug_vtk/joined_polydata.py
ladybug_vtk/metadata.py
ladybug_vtk/polydata.py
ladybug_vtk/visualization_set.py
ladybug_vtk/writer.py
ladybug_vtk/assets/PollinationViewer.html
ladybug_vtk/cli/__init__.py
ladybug_vtk/vtkjs/__init__.py
ladybug_vtk/vtkjs/helper.py
ladybug_vtk/vtkjs/schema.py
ladybug_vtk-0.15.2.dist-info/LICENSE
ladybug_vtk-0.15.2.dist-info/METADATA
ladybug_vtk-0.15.2.dist-info/WHEEL
ladybug_vtk-0.15.2.dist-info/entry_points.txt
ladybug_vtk-0.15.2.dist-info/top_level.txt
ladybug_vtk-0.15.2.dist-info/RECORD
