Metadata-Version: 2.1
Name: ladybug-vtk
Version: 0.15.2
Summary: Provides methods for translating ladybug-geometry objects to VTK PolyData.
Home-page: https://github.com/ladybug-tools/ladybug-vtk
Author: Ladybug Tools
Author-email: info@ladybug.tools
License: AGPL-3.0
Classifier: Programming Language :: Python :: 3.7
Classifier: Programming Language :: Python :: 3.10
Classifier: Programming Language :: Python :: Implementation :: CPython
Classifier: License :: OSI Approved :: GNU Affero General Public License v3
Classifier: Operating System :: OS Independent
License-File: LICENSE
Requires-Dist: ladybug-core>=0.42.37
Requires-Dist: ladybug-display-schema>=0.7.8
Requires-Dist: ladybug-display>=0.11.2
Requires-Dist: vtk>=9.1.0
Requires-Dist: pydantic<2.0
